{
  "db_name": "SQLite",
  "query": "\n        SELECT `parent_coin_id`, `puzzle_hash`, `amount`, `spent_height`, `created_height`, `transaction_id`, `kind`, `created_unixtime`, `spent_unixtime`\n        FROM `coin_states`\n        INNER JOIN `nft_coins` ON `coin_states`.coin_id = `nft_coins`.coin_id\n        WHERE `spent_height` IS NULL\n        AND `created_height` IS NOT NULL\n        ORDER BY `created_height`, `coin_states`.`coin_id` LIMIT ? OFFSET ?\n        ",
  "describe": {
    "columns": [
      {
        "name": "parent_coin_id",
        "ordinal": 0,
        "type_info": "Blob"
      },
      {
        "name": "puzzle_hash",
        "ordinal": 1,
        "type_info": "Blob"
      },
      {
        "name": "amount",
        "ordinal": 2,
        "type_info": "Blob"
      },
      {
        "name": "spent_height",
        "ordinal": 3,
        "type_info": "Integer"
      },
      {
        "name": "created_height",
        "ordinal": 4,
        "type_info": "Integer"
      },
      {
        "name": "transaction_id",
        "ordinal": 5,
        "type_info": "Blob"
      },
      {
        "name": "kind",
        "ordinal": 6,
        "type_info": "Integer"
      },
      {
        "name": "created_unixtime",
        "ordinal": 7,
        "type_info": "Integer"
      },
      {
        "name": "spent_unixtime",
        "ordinal": 8,
        "type_info": "Integer"
      }
    ],
    "parameters": {
      "Right": 2
    },
    "nullable": [
      false,
      false,
      false,
      true,
      true,
      true,
      false,
      true,
      true
    ]
  },
  "hash": "4feca15039a86c86f18e0019ebe51cab01b0552f3465c4b80ec24280d8ed50ca"
}
